KE/__init__.py
KE/base.py
KE/client.py
KE/const.py
KE/exceptions.py
KE/log.py
KE/util.py
KE/version.py
KE/v3/__init__.py
KE/v3/client.py
KE/v3/cube.py
KE/v3/job.py
KE/v3/model.py
KE/v3/project.py
KE/v3/query.py
KE/v3/segment.py
KE/v3/segments.py
KE/v3/user.py
KE/v4/__init__.py
KE/v4/client.py
KE/v4/job.py
KE/v4/model.py
KE/v4/project.py
KE/v4/query.py
KE/v4/segment.py
KE/v4/segments.py
KE/v4/user.py
examples/__init__.py
examples/example_build_segment.py
examples/example_build_segment_3x.py
examples/example_build_segment_4x.py
examples/example_compare_query_result.py
examples/example_compare_segments.py
examples/example_export_import_cubes.py
examples/example_merge_segment.py
examples/example_merge_segment_3x.py
examples/example_merge_segment_4x.py
examples/example_resume_failed_jobs.py
tests/__init__.py
tests/test_in_ipython.py
tests/test_util.py
tests/KE3/__init__.py
tests/KE3/test_client.py
tests/KE3/test_cube.py
tests/KE3/test_job.py
tests/KE3/test_model.py
tests/KE3/test_project.py
tests/KE3/test_query.py
tests/KE3/test_segment.py
tests/KE3/test_segments.py
tests/KE3/test_user.py
tests/KE4/__init__.py
tests/KE4/test_client.py
tests/KE4/test_job.py
tests/KE4/test_model.py
tests/KE4/test_project.py
tests/KE4/test_query.py
tests/KE4/test_segments.py
tests/KE4/test_user.py
KE_py-0.9.dist-info/METADATA
KE_py-0.9.dist-info/WHEEL
KE_py-0.9.dist-info/top_level.txt
KE_py-0.9.dist-info/RECORD
