Metadata-Version: 2.1
Name: KE-py
Version: 0.9
Summary: Python wrapper around the KE API
Home-page: https://github.com/Kyligence/KE-py
Author: dennis li
Author-email: xfl1991@163.com
License: MIT License
Download-URL: https://github.com/Kyligence/KE-py
Keywords: kyligence,kyligence enterprise,KE
Platform: UNKNOWN
Classifier: Intended Audience :: Developers
Classifier: License :: OSI Approved :: MIT License
Classifier: Operating System :: OS Independent
Classifier: Programming Language :: Python :: 2.7
Classifier: Programming Language :: Python :: 3.7
Requires-Dist: requests
Requires-Dist: pandas
Requires-Dist: ipython
Requires-Dist: six
